jooce/__init__.py
jooce/history.py
jooce/main.py
jooce/transcribe/__init__.py
Jooce-0.0.8.dist-info/METADATA
Jooce-0.0.8.dist-info/WHEEL
Jooce-0.0.8.dist-info/top_level.txt
Jooce-0.0.8.dist-info/RECORD
