Metadata-Version: 2.1
Name: Jooce
Version: 0.0.8
Summary: Simple and Easy Way to Recycle Boring Codes
Home-page: https://github.com/joos2010kj/Jooce
Author: Kevin Hyekang Joo
Author-email: joos2010kj@gmail.com
Classifier: Programming Language :: Python :: 3
Classifier: License :: OSI Approved :: MIT License
Classifier: Operating System :: OS Independent
